WeTest/__init__.py
WeTest/add.py
WeTest-0.0.1.dist-info/LICENSE
WeTest-0.0.1.dist-info/METADATA
WeTest-0.0.1.dist-info/WHEEL
WeTest-0.0.1.dist-info/top_level.txt
WeTest-0.0.1.dist-info/RECORD
