Metadata-Version: 2.1
Name: WeTest
Version: 0.0.1
Summary: SDK For Test Automation
Author-email: Huabo He <hhbstar@hotmail.com>
License: The MIT License (MIT)        
Project-URL: Homepage, https://github.com/baiyyee/WeTest
Project-URL: Issues, https://github.com/baiyyee/WeTest/issues
Classifier: Programming Language :: Python :: 3
Classifier: License :: OSI Approved :: MIT License
Classifier: Operating System :: OS Independent
Requires-Python: >=3.7
License-File: LICENSE
